freshdesk/__init__.py
freshdesk/api.py
freshdesk/base.py
freshdesk/client.py
freshdesk/constants.py
freshdesk/enumerators.py
freshdesk/errors.py
freshdesk/exceptions.py
freshdesk/limits.py
freshdesk/logger.py
freshdesk/models.py
freshdesk/typings.py
freshdesk/utilities.py
pyfreshdesk-0.1.13.dist-info/LICENSE
pyfreshdesk-0.1.13.dist-info/METADATA
pyfreshdesk-0.1.13.dist-info/WHEEL
pyfreshdesk-0.1.13.dist-info/top_level.txt
pyfreshdesk-0.1.13.dist-info/RECORD
