Metadata-Version: 2.2
Name: pyfreshdesk
Version: 0.1.13
Summary: Python client for Freshdesk API.
Author-email: "Kyle L. Davis" <aceofspades5757.github@gmail.com>
Maintainer-email: "Kyle L. Davis" <aceofspades5757.github@gmail.com>
License: MIT License
Project-URL: Homepage, https://github.com/AceofSpades5757/pyfreshdesk
Project-URL: Documentation, https://github.com/AceofSpades5757/pyfreshdesk/blob/main/README.md
Project-URL: Repository, https://github.com/AceofSpades5757/pyfreshdesk
Project-URL: Issues, https://github.com/AceofSpades5757/pyfreshdesk/issues
Keywords: freshdesk,api,client
Classifier: Development Status :: 4 - Beta
Classifier: Intended Audience :: Developers
Classifier: License :: OSI Approved :: MIT License
Classifier: Programming Language :: Python :: 3
Classifier: Programming Language :: Python :: 3.6
Classifier: Programming Language :: Python :: 3.7
Classifier: Programming Language :: Python :: 3.8
Classifier: Programming Language :: Python :: 3.9
Classifier: Programming Language :: Python :: 3.10
Classifier: Programming Language :: Python :: 3.11
Classifier: Programming Language :: Python :: 3.12
Classifier: Programming Language :: Python :: 3 :: Only
Classifier: Operating System :: OS Independent
Classifier: Topic :: Software Development :: Libraries
Classifier: Topic :: Software Development :: Libraries :: Python Modules
Requires-Python: >=3.6
License-File: LICENSE
Requires-Dist: requests
Requires-Dist: python-dateutil
Provides-Extra: dev
Requires-Dist: pre-commit; extra == "dev"
Requires-Dist: setuptools; extra == "dev"
Requires-Dist: build; extra == "dev"
Requires-Dist: twine; extra == "dev"
